mcp_server_shu1l/__init__.py
mcp_server_shu1l/__main__.py
mcp_server_shu1l/server.py
mcp_server_shu1l-0.2.4.dist-info/METADATA
mcp_server_shu1l-0.2.4.dist-info/WHEEL
mcp_server_shu1l-0.2.4.dist-info/entry_points.txt
mcp_server_shu1l-0.2.4.dist-info/top_level.txt
mcp_server_shu1l-0.2.4.dist-info/RECORD
